sarsen/__init__.py
sarsen/__main__.py
sarsen/apps.py
sarsen/chunking.py
sarsen/datamodel.py
sarsen/geocoding.py
sarsen/orbit.py
sarsen/py.typed
sarsen/radiometry.py
sarsen/scene.py
sarsen/sentinel1.py
sarsen/version.py
sarsen-0.9.5.dist-info/licenses/LICENSE
sarsen-0.9.5.dist-info/METADATA
sarsen-0.9.5.dist-info/WHEEL
sarsen-0.9.5.dist-info/entry_points.txt
sarsen-0.9.5.dist-info/top_level.txt
sarsen-0.9.5.dist-info/RECORD
