Metadata-Version: 2.4
Name: sarsen
Version: 0.9.5
Summary: Algorithms and utilities for Synthetic Aperture Radar (SAR) sensors
License:                                  Apache License
Classifier: Development Status :: 4 - Beta
Classifier: Intended Audience :: Science/Research
Classifier: License :: OSI Approved :: Apache Software License
Classifier: Operating System :: OS Independent
Classifier: Programming Language :: Python
Classifier: Programming Language :: Python :: 3
Classifier: Programming Language :: Python :: 3.10
Classifier: Programming Language :: Python :: 3.11
Classifier: Programming Language :: Python :: 3.12
Classifier: Programming Language :: Python :: 3.13
Classifier: Topic :: Scientific/Engineering
Requires-Python: >=3.10
License-File: LICENSE
Requires-Dist: attrs>=24.0
Requires-Dist: dask>=2023.2.0
Requires-Dist: flox>=0.9.13
Requires-Dist: numpy>=1.23.0
Requires-Dist: pandas>=1.4.0
Requires-Dist: rioxarray>=0.15.0
Requires-Dist: typer>=0.11
Requires-Dist: xarray>=2023.12.0
Requires-Dist: xarray-sentinel>=0.9.3
Dynamic: license-file
